trodi/__init__.py
trodi/cli.py
trodi/core.py
trodi/deramp.py
trodi/logger.py
trodi/plotting.py
trodi/sario.py
trodi/utils.py
trodi-0.2.4.dist-info/LICENSE.txt
trodi-0.2.4.dist-info/METADATA
trodi-0.2.4.dist-info/WHEEL
trodi-0.2.4.dist-info/entry_points.txt
trodi-0.2.4.dist-info/top_level.txt
trodi-0.2.4.dist-info/RECORD
