Metadata-Version: 2.1
Name: trodi
Version: 0.2.4
Summary: Label interferogram pixels or images as outliers
Home-page: https://github.com/scottstanie/trodi/
Author: scott
Author-email: scott.stanie@gmail.com
License: mit
Platform: any
Classifier: Development Status :: 4 - Beta
Classifier: Programming Language :: Python
License-File: LICENSE.txt
Requires-Dist: numpy (>=1.16.0)
Requires-Dist: xarray (>=0.16.1)
Requires-Dist: h5py (>3.3)
Requires-Dist: h5netcdf
Requires-Dist: cftime
Provides-Extra: gdal
Requires-Dist: gdal ; extra == 'gdal'
